odoo10_addon_stock_picking_invoice_link-10.0.1.0.0-py2.7-nspkg.pth
odoo/addons/stock_picking_invoice_link/README.rst
odoo/addons/stock_picking_invoice_link/__init__.py
odoo/addons/stock_picking_invoice_link/__manifest__.py
odoo/addons/stock_picking_invoice_link/i18n/de.po
odoo/addons/stock_picking_invoice_link/i18n/es.po
odoo/addons/stock_picking_invoice_link/i18n/fi.po
odoo/addons/stock_picking_invoice_link/i18n/fr.po
odoo/addons/stock_picking_invoice_link/i18n/it.po
odoo/addons/stock_picking_invoice_link/i18n/pt_BR.po
odoo/addons/stock_picking_invoice_link/i18n/sl.po
odoo/addons/stock_picking_invoice_link/models/__init__.py
odoo/addons/stock_picking_invoice_link/models/account_invoice.py
odoo/addons/stock_picking_invoice_link/models/sale_order.py
odoo/addons/stock_picking_invoice_link/models/stock_move.py
odoo/addons/stock_picking_invoice_link/models/stock_picking.py
odoo/addons/stock_picking_invoice_link/static/description/icon.png
odoo/addons/stock_picking_invoice_link/tests/__init__.py
odoo/addons/stock_picking_invoice_link/tests/test_stock_picking_invoice_link.py
odoo/addons/stock_picking_invoice_link/views/account_invoice_view.xml
odoo/addons/stock_picking_invoice_link/views/stock_view.xml
odoo10_addon_stock_picking_invoice_link-10.0.1.0.0.dist-info/DESCRIPTION.rst
odoo10_addon_stock_picking_invoice_link-10.0.1.0.0.dist-info/METADATA
odoo10_addon_stock_picking_invoice_link-10.0.1.0.0.dist-info/RECORD
odoo10_addon_stock_picking_invoice_link-10.0.1.0.0.dist-info/WHEEL
odoo10_addon_stock_picking_invoice_link-10.0.1.0.0.dist-info/metadata.json
odoo10_addon_stock_picking_invoice_link-10.0.1.0.0.dist-info/namespace_packages.txt
odoo10_addon_stock_picking_invoice_link-10.0.1.0.0.dist-info/top_level.txt
